Metadata-Version: 2.4
Name: roshambo2
Version: 2.0.0
Summary: 3D molecular shape overlap
License: MIT License
Project-URL: Homepage, https://github.com/molecularinformatics/roshambo2
Classifier: Programming Language :: Python :: 3
Classifier: License :: OSI Approved :: MIT License
Classifier: Programming Language :: C++
Classifier: Topic :: Scientific/Engineering :: Chemistry
Requires-Python: >=3.11
License-File: LICENSE
Requires-Dist: numpy
Requires-Dist: scipy
Requires-Dist: rdkit
Requires-Dist: tqdm
Requires-Dist: h5py
Requires-Dist: psutil
Requires-Dist: flask
Requires-Dist: requests
Requires-Dist: pyyaml
Dynamic: license-file
